tests/__init__.py
tests/test_ustrid.py
ustrid/__init__.py
ustrid/__main__.py
ustrid-0.0.2.dist-info/LICENSE
ustrid-0.0.2.dist-info/METADATA
ustrid-0.0.2.dist-info/WHEEL
ustrid-0.0.2.dist-info/entry_points.txt
ustrid-0.0.2.dist-info/top_level.txt
ustrid-0.0.2.dist-info/RECORD
